ollagents/__init__.py
ollagents/agent.py
ollagents/tools.py
ollagents-0.1.1.dist-info/METADATA
ollagents-0.1.1.dist-info/WHEEL
ollagents-0.1.1.dist-info/top_level.txt
ollagents-0.1.1.dist-info/RECORD
