Metadata-Version: 2.1
Name: ollagents
Version: 0.1.1
Summary: The simplest AI agents
Author: Hugo Ventura
Requires-Python: >=3.10
Requires-Dist: ollama
